setup.py
amqping/__init__.py
amqping.egg-info/PKG-INFO
amqping.egg-info/SOURCES.txt
amqping.egg-info/dependency_links.txt
amqping.egg-info/entry_points.txt
amqping.egg-info/pbr.json
amqping.egg-info/requires.txt
amqping.egg-info/top_level.txt