Metadata-Version: 1.0
Name: amqping
Version: 0.3
Summary: simple package/command for tesitng if an amqp instance is responding
Home-page: https://github.com/hughsaunders/amqping
Author: Hugh Saunders
Author-email: hugh@wherenow.org
License: Apache
Keywords: amqp rabbitmq ping
Platform: UNKNOWN
